gptcachelite/__init__.py
gptcachelite/main.py
gptcachelite-1.1.0.dist-info/LICENSE
gptcachelite-1.1.0.dist-info/METADATA
gptcachelite-1.1.0.dist-info/WHEEL
gptcachelite-1.1.0.dist-info/top_level.txt
gptcachelite-1.1.0.dist-info/RECORD
